maap_help_jupyter_extension/__init__.py
maap_help_jupyter_extension/_version.py
maap_help_jupyter_extension-2.0.2.data/data/share/jupyter/labextensions/maap-help-jupyter-extension/build_log.json
maap_help_jupyter_extension-2.0.2.data/data/share/jupyter/labextensions/maap-help-jupyter-extension/package.json
maap_help_jupyter_extension-2.0.2.data/data/share/jupyter/labextensions/maap-help-jupyter-extension/schemas/maap-help-jupyter-extension/package.json.orig
maap_help_jupyter_extension-2.0.2.data/data/share/jupyter/labextensions/maap-help-jupyter-extension/schemas/maap-help-jupyter-extension/plugin.json
maap_help_jupyter_extension-2.0.2.data/data/share/jupyter/labextensions/maap-help-jupyter-extension/static/lib_index_js.4fa28170faf945b1ab14.js
maap_help_jupyter_extension-2.0.2.data/data/share/jupyter/labextensions/maap-help-jupyter-extension/static/lib_index_js.4fa28170faf945b1ab14.js.map
maap_help_jupyter_extension-2.0.2.data/data/share/jupyter/labextensions/maap-help-jupyter-extension/static/remoteEntry.0af3776711bfcc16ef88.js
maap_help_jupyter_extension-2.0.2.data/data/share/jupyter/labextensions/maap-help-jupyter-extension/static/remoteEntry.0af3776711bfcc16ef88.js.map
maap_help_jupyter_extension-2.0.2.data/data/share/jupyter/labextensions/maap-help-jupyter-extension/static/style.js
maap_help_jupyter_extension-2.0.2.data/data/share/jupyter/labextensions/maap-help-jupyter-extension/static/style_index_js.17478ca6fbd5977393d4.js
maap_help_jupyter_extension-2.0.2.data/data/share/jupyter/labextensions/maap-help-jupyter-extension/static/style_index_js.17478ca6fbd5977393d4.js.map
maap_help_jupyter_extension-2.0.2.data/data/share/jupyter/labextensions/maap-help-jupyter-extension/static/vendors-node_modules_react-joyride_dist_index_mjs-node_modules_css-loader_dist_runtime_api_js-f70e70.0611c1b59cfc44a0e98f.js
maap_help_jupyter_extension-2.0.2.dist-info/METADATA
maap_help_jupyter_extension-2.0.2.dist-info/WHEEL
maap_help_jupyter_extension-2.0.2.dist-info/licenses/LICENSE
maap_help_jupyter_extension-2.0.2.dist-info/RECORD
